mypandas/__init__.py
mypandas/sqldf.py
mypandas/data/births.csv
mypandas/data/births_by_month.csv
mypandas/data/meat.csv
mypandas-0.1.6.dist-info/METADATA
mypandas-0.1.6.dist-info/WHEEL
mypandas-0.1.6.dist-info/licenses/LICENSE
mypandas-0.1.6.dist-info/RECORD
