Metadata-Version: 2.1
Name: mypandas
Version: 0.1.6
Summary: Query Panadas DataFrames with SQL
Project-URL: Homepage, https://github.com/yrom1/mypandas
Project-URL: Bug Tracker, https://github.com/yrom1/mypandas/issues
Author-email: yrom1 <ryanm.inbox@gmail.com>
License-File: LICENSE
Classifier: License :: OSI Approved :: MIT License
Classifier: Operating System :: OS Independent
Classifier: Programming Language :: Python :: 3
Requires-Python: >=3.10
Requires-Dist: mysqlclient
Requires-Dist: pandas
Requires-Dist: sqlalchemy
